face_xjx7/__init__.py
face_xjx7/config/__init__.py
face_xjx7/core/__init__.py
face_xjx7/core/image_cropper/BaseImageCropper.py
face_xjx7/core/image_cropper/__init__.py
face_xjx7/core/image_cropper/arcface_face_recognition/FaceRecImageCropper.py
face_xjx7/core/image_cropper/arcface_face_recognition/__init__.py
face_xjx7/core/model_handler/BaseModelHandler.py
face_xjx7/core/model_handler/__init__.py
face_xjx7/core/model_handler/face_detection/FaceDetModelHandler.py
face_xjx7/core/model_handler/face_detection/__init__.py
face_xjx7/core/model_handler/face_landmark/FaceLmsModelHandler.py
face_xjx7/core/model_handler/face_landmark/__init__.py
face_xjx7/core/model_handler/face_recognition/FaceRecModelHandler.py
face_xjx7/core/model_handler/face_recognition/__init__.py
face_xjx7/core/model_loader/BaseModelLoader.py
face_xjx7/core/model_loader/__init__.py
face_xjx7/core/model_loader/face_detection/FaceDetModelLoader.py
face_xjx7/core/model_loader/face_detection/__init__.py
face_xjx7/core/model_loader/face_landmark/FaceLmsModelLoader.py
face_xjx7/core/model_loader/face_landmark/__init__.py
face_xjx7/core/model_loader/face_recognition/FaceRecModelLoader.py
face_xjx7/core/model_loader/face_recognition/__init__.py
face_xjx7/logs/__init__.py
face_xjx7/models/__init__.py
face_xjx7/models/face_detection/__init__.py
face_xjx7/models/face_landmark/__init__.py
face_xjx7/models/face_recognition/__init__.py
face_xjx7/models/network_def/__init__.py
face_xjx7/models/network_def/mobilefacenet_def.py
face_xjx7/models/network_def/mobilev3_pfld.py
face_xjx7/models/network_def/retinaface_def.py
face_xjx7/models/network_def/retinaface_def_resnet.py
face_xjx7/sample_api/__init__.py
face_xjx7/sample_api/sample_face_crop.py
face_xjx7/sample_api/sample_face_detect.py
face_xjx7/sample_api/sample_face_feature.py
face_xjx7/sample_api/sample_face_landmark.py
face_xjx7/sample_api/sample_face_pipline.py
face_xjx7/sample_api/temp/__init__.py
face_xjx7/sample_api/test_image/__init__.py
face_xjx7-0.0.8.dist-info/LICENSE
face_xjx7-0.0.8.dist-info/METADATA
face_xjx7-0.0.8.dist-info/WHEEL
face_xjx7-0.0.8.dist-info/top_level.txt
face_xjx7-0.0.8.dist-info/RECORD
