Metadata-Version: 2.1
Name: face-xjx7
Version: 0.0.8
Summary: try to put on pip to install
Home-page: https://github.com/XJX777
Author: xjx this is me
Author-email: jixuanxu@163.com
License: UNKNOWN
Platform: UNKNOWN
Classifier: Programming Language :: Python :: 3
Classifier: License :: OSI Approved :: MIT License
Classifier: Operating System :: OS Independent
